CHANGELOG.txt
LICENSE.txt
MANIFEST.in
README.md
__init__.py
setup.py
polynomial_fit/__init__.py
polynomial_fit.egg-info/PKG-INFO
polynomial_fit.egg-info/SOURCES.txt
polynomial_fit.egg-info/dependency_links.txt
polynomial_fit.egg-info/top_level.txt