Metadata-Version: 2.2
Name: polynomial-fit
Version: 0.0.2
Summary: Fit a polynomial of any order and dimension to a dataset
Home-page: 
Author: Seth Reed
Author-email: seth.reed01@gmail.com
License: MIT
Keywords: polynomial
Classifier: Development Status :: 5 - Production/Stable
Classifier: Intended Audience :: Education
Classifier: Operating System :: Microsoft :: Windows :: Windows 10
Classifier: License :: OSI Approved :: MIT License
Classifier: Programming Language :: Python :: 3
License-File: LICENSE.txt
Dynamic: author
Dynamic: author-email
Dynamic: classifier
Dynamic: description
Dynamic: description-content-type
Dynamic: keywords
Dynamic: license
Dynamic: summary
